pypath.py
setup.py
pypath.egg-info/PKG-INFO
pypath.egg-info/SOURCES.txt
pypath.egg-info/dependency_links.txt
pypath.egg-info/top_level.txt