Metadata-Version: 1.0
Name: pypath
Version: 0.1
Summary: Minimalistic replacement for py.path.local
Home-page: http://bitbucket.org/antocuni/pypath
Author: Antonio Cuni
Author-email: anto.cuni@gmail.com
License: BSD
Platform: UNKNOWN
